pyllusion/__init__.py
pyllusion/Autostereogram/Autostereogram.py
pyllusion/Autostereogram/__init__.py
pyllusion/Contrast/Contrast.py
pyllusion/Contrast/__init__.py
pyllusion/Contrast/contrast_image.py
pyllusion/Contrast/contrast_parameters.py
pyllusion/Contrast/contrast_psychopy.py
pyllusion/Delboeuf/Delboeuf.py
pyllusion/Delboeuf/__init__.py
pyllusion/Delboeuf/delboeuf_image.py
pyllusion/Delboeuf/delboeuf_parameters.py
pyllusion/Delboeuf/delboeuf_psychopy.py
pyllusion/Ebbinghaus/Ebbinghaus.py
pyllusion/Ebbinghaus/__init__.py
pyllusion/Ebbinghaus/ebbinghaus_image.py
pyllusion/Ebbinghaus/ebbinghaus_parameters.py
pyllusion/Ebbinghaus/ebbinghaus_psychopy.py
pyllusion/MullerLyer/MullerLyer.py
pyllusion/MullerLyer/__init__.py
pyllusion/MullerLyer/mullerlyer_image.py
pyllusion/MullerLyer/mullerlyer_parameters.py
pyllusion/MullerLyer/mullerlyer_psychopy.py
pyllusion/Pareidolia/Pareidolia.py
pyllusion/Pareidolia/__init__.py
pyllusion/Poggendorff/Poggendorff.py
pyllusion/Poggendorff/__init__.py
pyllusion/Poggendorff/poggendorff_image.py
pyllusion/Poggendorff/poggendorff_parameters.py
pyllusion/Poggendorff/poggendorff_psychopy.py
pyllusion/Ponzo/Ponzo.py
pyllusion/Ponzo/__init__.py
pyllusion/Ponzo/ponzo_image.py
pyllusion/Ponzo/ponzo_parameters.py
pyllusion/Ponzo/ponzo_psychopy.py
pyllusion/RodFrame/RodFrame.py
pyllusion/RodFrame/__init__.py
pyllusion/RodFrame/rodframe_image.py
pyllusion/RodFrame/rodframe_parameters.py
pyllusion/RodFrame/rodframe_psychopy.py
pyllusion/VerticalHorizontal/VerticalHorizontal.py
pyllusion/VerticalHorizontal/__init__.py
pyllusion/VerticalHorizontal/verticalhorizontal_image.py
pyllusion/VerticalHorizontal/verticalhorizontal_parameters.py
pyllusion/VerticalHorizontal/verticalhorizontal_psychopy.py
pyllusion/White/White.py
pyllusion/White/__init__.py
pyllusion/White/white_image.py
pyllusion/White/white_parameters.py
pyllusion/White/white_psychopy.py
pyllusion/Zollner/Zollner.py
pyllusion/Zollner/__init__.py
pyllusion/Zollner/zollner_image.py
pyllusion-1.3.dist-info/LICENSE
pyllusion-1.3.dist-info/METADATA
pyllusion-1.3.dist-info/WHEEL
pyllusion-1.3.dist-info/top_level.txt
pyllusion-1.3.dist-info/RECORD
