Metadata-Version: 2.1
Name: pyllusion
Version: 1.3
Summary: A Parametric Framework to Generate Visual Illusions.
Home-page: https://github.com/RealityBending/Pyllusion/
Download-URL: https://github.com/RealityBending/Pyllusion/zipball/master
Author: Dominique Makowski
Author-email: dom.makowski@gmail.com
Maintainer: Dominique Makowski
Maintainer-email: dom.makowski@gmail.com
License: Mozilla Public License Version 2.0
Keywords: python pyllusion visual optical illusions
Classifier: Intended Audience :: Science/Research
Classifier: Intended Audience :: Developers
Classifier: Programming Language :: Python
Classifier: Topic :: Software Development
Classifier: Topic :: Scientific/Engineering
Classifier: Operating System :: Microsoft :: Windows
Classifier: Operating System :: Unix
Classifier: Operating System :: MacOS
Classifier: Programming Language :: Python :: 3.5
Classifier: Programming Language :: Python :: 3.6
License-File: LICENSE
Requires-Dist: numpy
Requires-Dist: pandas
Requires-Dist: Pillow
Requires-Dist: scipy
Provides-Extra: test
Requires-Dist: numpy; extra == "test"
Requires-Dist: pandas; extra == "test"
Requires-Dist: Pillow; extra == "test"
Requires-Dist: scipy; extra == "test"
Requires-Dist: pytest; extra == "test"
Requires-Dist: matplotlib; extra == "test"
Requires-Dist: coverage; extra == "test"
Requires-Dist: scikit-image; extra == "test"
